__init__.py
common/__init__.py
common/service.py
common/constants/__init__.py
common/constants/constant.py
common/constants/customer.py
common/constants/product.py
coupon/__init__.py
coupon/coupon.py
customer/__init__.py
customer/customer.py
exceptions/__init__.py
exceptions/exception_constants.py
exceptions/exception_handling.py
price/__init__.py
price/price.py
product/__init__.py
product/product.py
promo_code/__init__.py
promo_code/promo_code.py
subscription/__init__.py
subscription/subscription.py
subscription_schedule/__init__.py
subscription_schedule/subscription_schedule.py
stripe_package_STONEAGEFIRE-0.0.6.dist-info/LICENSE
stripe_package_STONEAGEFIRE-0.0.6.dist-info/METADATA
stripe_package_STONEAGEFIRE-0.0.6.dist-info/WHEEL
stripe_package_STONEAGEFIRE-0.0.6.dist-info/top_level.txt
stripe_package_STONEAGEFIRE-0.0.6.dist-info/RECORD
