Metadata-Version: 2.1
Name: stripe-package-STONEAGEFIRE
Version: 0.0.6
Summary: stripe custom package for faster and easier integration of stripe api in python
Author-email: Soham Patel <soham.patel@electrumitsolutions.com>
Project-URL: Homepage, https://github.com/stoneagefire/stripe-package-api
Project-URL: Bug Tracker, https://github.com/stoneagefire/stripe-package-api/issues
Classifier: Programming Language :: Python :: 3
Classifier: License :: OSI Approved :: MIT License
Classifier: Operating System :: OS Independent
Requires-Python: >=3.7
License-File: LICENSE
